CachiPy.py
CachiPy-0.0.5.dist-info/LICENSE
CachiPy-0.0.5.dist-info/METADATA
CachiPy-0.0.5.dist-info/WHEEL
CachiPy-0.0.5.dist-info/top_level.txt
CachiPy-0.0.5.dist-info/RECORD
