Metadata-Version: 2.1
Name: CachiPy
Version: 0.0.5
Summary: A caching library specially designed for FastAPI
Home-page: UNKNOWN
Author: Ambar Rizvi
Author-email: <brannstrom9911@gmail.com>
License: UNKNOWN
Keywords: cache,caching,API response,API caching,FastAPI cache,FastAPI caching,fastapi cacher
Platform: UNKNOWN
Classifier: Development Status :: 2 - Pre-Alpha
Classifier: Intended Audience :: Developers
Classifier: Programming Language :: Python :: 3
Classifier: License :: OSI Approved :: MIT License
Classifier: Operating System :: Unix
Classifier: Operating System :: MacOS :: MacOS X
Classifier: Operating System :: Microsoft :: Windows
License-File: LICENSE
